abbreviations/__init__.py
abbreviations/schwartz_hearst.py
abbreviations-0.2.5.dist-info/LICENSE.txt
abbreviations-0.2.5.dist-info/METADATA
abbreviations-0.2.5.dist-info/WHEEL
abbreviations-0.2.5.dist-info/top_level.txt
abbreviations-0.2.5.dist-info/RECORD
